{
  "confirmDeletion": false,
  "showAddCommand": true,
  "debug": false,
  "editorMenu": [],
  "fileMenu": [
    {
      "id": "workspace:edit-file-title",
      "icon": "lucide-edit-3",
      "name": "编辑文件名",
      "mode": "any"
    },
    {
      "id": "Enhanced-editing:edit-duanhang",
      "icon": "alert-triangle",
      "name": "增强编辑: 修复意外断行",
      "mode": "any"
    }
  ],
  "leftRibbon": [
    {
      "id": "file-explorer:reveal-active-file",
      "icon": "lucide-navigation",
      "name": "显示当前文件",
      "mode": "any"
    }
  ],
  "rightRibbon": [],
  "titleBar": [],
  "statusBar": [
    {
      "id": "workspace:toggle-pin",
      "icon": "lucide-pin",
      "name": "解锁/锁定",
      "mode": "any"
    },
    {
      "id": "workspace:export-pdf",
      "icon": "arrow-up-circle",
      "name": "导出为 PDF",
      "mode": "any"
    }
  ],
  "pageHeader": [
    {
      "id": "random-note",
      "icon": "dice-glyph",
      "name": "漫游笔记: 开始漫游笔记",
      "mode": "7712896608861b4d",
      "color": "#000000"
    },
    {
      "id": "obsidian-markmind:Toggle to markdown or mindmap",
      "icon": "box",
      "name": "obsidian markmind: 切换为Markdown或思维导图模式",
      "mode": "7712896608861b4d"
    },
    {
      "id": "workspace:undo-close-pane",
      "icon": "lucide-undo-2",
      "name": "Undo close tab",
      "mode": "7712896608861b4d",
      "color": "#000000"
    },
    {
      "id": "obsidian-markmind:Change basic to table mode",
      "icon": "align-justify",
      "name": "obsidian markmind: 打开 Basic 模式的思维导图为表格",
      "mode": "mobile"
    },
    {
      "id": "digitalgarden:publish-note",
      "icon": "activity",
      "name": "Digital Garden: Publish Single Note",
      "mode": "7712896608861b4d"
    }
  ],
  "macros": [
    {
      "macro": [
        {
          "action": 0,
          "commandId": "remotely-save:start-sync"
        },
        {
          "action": 0,
          "commandId": "obsidian-omnivore:sync"
        },
        {
          "action": 0,
          "commandId": "obsidian-weread-plugin:sync-weread-notes-command"
        }
      ],
      "name": "开机自启动",
      "icon": "star",
      "startup": true
    }
  ],
  "explorer": [],
  "hide": {
    "statusbar": [
      "cmenu-plugin",
      "flashcards-obsidian",
      "obsidian-day-planner",
      "obsidian-spaced-repetition-recall"
    ],
    "leftRibbon": [
      "开始漫游笔记",
      "新建白板",
      "打开 Markdown 格式转换器",
      "开始/结束录音",
      "管理工作区布局",
      "打开快速切换",
      "Templater",
      "插入模板",
      "打开命令面板",
      "Timeline",
      "BRAT",
      "打开新词面板",
      "打开查词面板",
      "Omnisearch",
      "surfing-bookmark-manager",
      "Big Calendar",
      "Extract Highlights"
    ]
  },
  "spacing": "6",
  "advancedToolbar": {
    "rowHeight": 48,
    "rowCount": 1,
    "spacing": 0,
    "buttonWidth": 48,
    "columnLayout": false,
    "mappedIcons": [],
    "tooltips": false,
    "heightOffset": 0
  }
}